videosdk/plugins/humeai/__init__.py
videosdk/plugins/humeai/tts.py
videosdk/plugins/humeai/version.py
videosdk_plugins_humeai-0.0.58.dist-info/METADATA
videosdk_plugins_humeai-0.0.58.dist-info/WHEEL
videosdk_plugins_humeai-0.0.58.dist-info/RECORD
