Metadata-Version: 2.4
Name: videosdk-plugins-humeai
Version: 0.0.58
Summary: Hume AI TTS plugin for videosdk-agents
Author: videosdk
License-Expression: Apache-2.0
Keywords: agents,ai,hume,humeai,text-to-speech,tts,videosdk,voice
Classifier: Development Status :: 4 - Beta
Classifier: Intended Audience :: Developers
Classifier: Topic :: Communications :: Conferencing
Classifier: Topic :: Multimedia :: Sound/Audio
Classifier: Topic :: Multimedia :: Video
Classifier: Topic :: Scientific/Engineering :: Artificial Intelligence
Requires-Python: >=3.11
Requires-Dist: httpx>=0.24.0
Requires-Dist: numpy
Requires-Dist: scipy>=1.11.0
Requires-Dist: videosdk-agents>=0.0.58
